fx_rr.py
fx_rr-0.1.0.dist-info/METADATA
fx_rr-0.1.0.dist-info/WHEEL
fx_rr-0.1.0.dist-info/top_level.txt
fx_rr-0.1.0.dist-info/RECORD
